scripto/ArgParserUtils.py
scripto/FuncUtils.py
scripto/FunctionData.py
scripto/__init__.py
scripto/app.py
scripto/wrap/__main__.py
Scripto-2.0.14.dist-info/LICENSE.txt
Scripto-2.0.14.dist-info/METADATA
Scripto-2.0.14.dist-info/WHEEL
Scripto-2.0.14.dist-info/top_level.txt
Scripto-2.0.14.dist-info/RECORD
