Metadata-Version: 2.1
Name: Scripto
Version: 2.0.14
Summary: A simple framework to help you build scripts faster!
Author-email: Ron Hasleton <ronhasleton@gmail.com>
License:                     GNU GENERAL PUBLIC LICENSE
Project-URL: Repository, https://github.com/rhron255/Scripto
Project-URL: Issues, https://github.com/rhron255/Scripto/issues
Classifier: Development Status :: 3 - Alpha
Classifier: Intended Audience :: Developers
Requires-Python: >=3.8
License-File: LICENSE.txt
